locust/__init__.py
locust/__main__.py
locust/_version.py
locust/argument_parser.py
locust/clients.py
locust/debug.py
locust/dispatch.py
locust/env.py
locust/event.py
locust/exception.py
locust/html.py
locust/input_events.py
locust/log.py
locust/main.py
locust/py.typed
locust/runners.py
locust/shape.py
locust/stats.py
locust/web.py
locust/contrib/__init__.py
locust/contrib/fasthttp.py
locust/contrib/milvus.py
locust/contrib/mongodb.py
locust/contrib/mqtt.py
locust/contrib/oai.py
locust/contrib/postgres.py
locust/contrib/socketio.py
locust/rpc/__init__.py
locust/rpc/protocol.py
locust/rpc/zmqrpc.py
locust/user/__init__.py
locust/user/inspectuser.py
locust/user/markov_taskset.py
locust/user/sequential_taskset.py
locust/user/task.py
locust/user/users.py
locust/user/wait_time.py
locust/util/__init__.py
locust/util/cache.py
locust/util/date.py
locust/util/deprecation.py
locust/util/directory.py
locust/util/exception_handler.py
locust/util/load_locustfile.py
locust/util/rounding.py
locust/util/timespan.py
locust/util/url.py
locust/webui/dist/auth.html
locust/webui/dist/index.html
locust/webui/dist/report.html
locust/webui/dist/assets/favicon-dark.png
locust/webui/dist/assets/favicon-light.png
locust/webui/dist/assets/graphs-dark.png
locust/webui/dist/assets/graphs-light.png
locust/webui/dist/assets/index-aozIzkOV.js
locust/webui/dist/assets/terminal.gif
locust/webui/dist/assets/testruns-dark.png
locust/webui/dist/assets/testruns-light.png
pytest_locust/plugin.py
locust-2.41.0.dist-info/METADATA
locust-2.41.0.dist-info/WHEEL
locust-2.41.0.dist-info/entry_points.txt
locust-2.41.0.dist-info/licenses/LICENSE
locust-2.41.0.dist-info/RECORD
